[
	{
		"__TYPE__": "SharedSliceContent",
		"variation": "default",
		"primary": {
			"picture": {
				"provider": "imgix",
				"url": "https://images.unsplash.com/photo-1628945301291-a19611e106a7?crop=entropy&cs=srgb&fm=jpg&ixid=M3wzMzc0NjN8MHwxfHNlYXJjaHw4fHxmaWxtJTIwcGhvdG9ncmFwaHl8ZW58MHx8fHwxNzUyNTczMTM3fDA&ixlib=rb-4.1.0&q=85",
				"alt": "pink flower field near body of water during daytime",
				"origin": {
					"id": "StQJj4NAYg0",
					"url": "https://images.unsplash.com/photo-1628945301291-a19611e106a7?crop=entropy&cs=srgb&fm=jpg&ixid=M3wzMzc0NjN8MHwxfHNlYXJjaHw4fHxmaWxtJTIwcGhvdG9ncmFwaHl8ZW58MHx8fHwxNzUyNTczMTM3fDA&ixlib=rb-4.1.0&q=85",
					"width": 3130,
					"height": 2075
				},
				"width": 3130,
				"height": 2075,
				"edit": {
					"background": "transparent",
					"zoom": 1,
					"crop": {
						"x": 0,
						"y": 0
					}
				},
				"credits": null,
				"__TYPE__": "ImageContent",
				"thumbnails": {}
			},
			"caption": {
				"__TYPE__": "StructuredTextContent",
				"value": [
					{
						"type": "paragraph",
						"content": {
							"text": "Flower field by @lihbr.png. 1/250s, f/2.8, 50mm, with Farbe 400.",
							"spans": [
								{
									"type": "hyperlink",
									"start": 16,
									"end": 26,
									"data": {
										"__TYPE__": "ExternalLink",
										"url": "https://www.instagram.com/lihbr.png",
										"target": "_blank"
									}
								},
								{
									"type": "hyperlink",
									"start": 54,
									"end": 63,
									"data": {
										"__TYPE__": "ExternalLink",
										"url": "#400",
										"target": "_self"
									}
								}
							]
						},
						"direction": "ltr"
					}
				]
			},
			"product": {
				"key": "20d2408f-2c19-4805-a6bd-fb39f1571e95",
				"__TYPE__": "LinkContent",
				"value": {
					"__TYPE__": "DocumentLink",
					"id": "mock_document_id"
				}
			}
		},
		"items": []
	},
	{
		"__TYPE__": "SharedSliceContent",
		"variation": "reversed",
		"primary": {
			"picture": {
				"origin": {
					"id": "main",
					"url": "https://images.unsplash.com/photo-1589321578146-4c1ba445cc88",
					"width": 3168,
					"height": 4752
				},
				"url": "https://images.unsplash.com/photo-1589321578146-4c1ba445cc88",
				"width": 3168,
				"height": 4752,
				"edit": {
					"zoom": 1,
					"crop": {
						"x": 0,
						"y": 0
					},
					"background": "transparent"
				},
				"alt": "driver",
				"credits": null,
				"__TYPE__": "ImageContent",
				"thumbnails": {}
			},
			"caption": {
				"__TYPE__": "StructuredTextContent",
				"value": [
					{
						"type": "paragraph",
						"content": {
							"text": "Consequat fugiat ut pariatur velit aute sunt. Duis irure aute qui dolor laboris labore labore aute nostrud anim est ullamco magna sunt."
						}
					}
				]
			},
			"secondary_picture": {
				"origin": {
					"id": "main",
					"url": "https://images.unsplash.com/photo-1587614295999-6c1c13675117",
					"width": 3810,
					"height": 5715
				},
				"url": "https://images.unsplash.com/photo-1587614295999-6c1c13675117",
				"width": 3810,
				"height": 5715,
				"edit": {
					"zoom": 1,
					"crop": {
						"x": 0,
						"y": 0
					},
					"background": "transparent"
				},
				"alt": "person",
				"credits": null,
				"__TYPE__": "ImageContent",
				"thumbnails": {}
			},
			"secondary_caption": {
				"__TYPE__": "StructuredTextContent",
				"value": [
					{
						"type": "paragraph",
						"content": {
							"text": "Reprehenderit mollit veniam consectetur. Voluptate commodo reprehenderit Lorem esse sunt nisi deserunt minim enim. Aliquip cupidatat dolore aliqua reprehenderit occaecat."
						}
					}
				]
			},
			"product": {
				"key": "3d4d0eef-4e97-4be2-a67c-d8094cdc4561",
				"__TYPE__": "LinkContent",
				"value": {
					"__TYPE__": "DocumentLink",
					"id": "mock_document_id"
				}
			}
		},
		"items": [
			{
				"__TYPE__": "GroupItemContent",
				"value": []
			}
		]
	}
]